Verilog/example.v
 module example(Y,A,B,C,D,E,F);
 input A,B,C,D,E,F;
 output Y;
 wire t1,t2,t3;
 nand #1 G1(t1,A,B);
 and #2 G2(t2,A,~B,C,D);
 nor #1 G3(t3,E,F);
 nand #1 G4(Y,t1,t2,t3);
 
 endmodule

Verilog/example_one_tb.v
`include "example.v"


module example_tb;
reg A,B,C,D,E,F;
wire Y;
example example_1(Y,A,B,C,D,E,F);

initial
begin
    $dumpfile("example_tb_one.vcd");
    $dumpvars(0, example_tb);
    $monitor($time,"A=%b,B=%b,C=%b,D=%b,E=%b,F=%b",A,B,C,D,E,F,Y);
    A=0;B=0;C=0;D=0;E=0;F=0;
    #5 A=1;B=0;C=0;D=1;E=0;F=0;
    #5 A=0;B=0;C=1;D=1;E=0;F=0;
    #5 A=1;C=0;
    #5 F=1;
    #5 $finish;
end
endmodule

Verilog/example_tb_one.vcd
$date
	Tue Dec 06 10:51:14 2022
$end
$version
	Icarus Verilog
$end
$timescale
	1s
$end
$scope module example_tb $end
$var wire 1 ! Y $end
$var reg 1 " A $end
$var reg 1 # B $end
$var reg 1 $ C $end
$var reg 1 % D $end
$var reg 1 & E $end
$var reg 1 ' F $end
$scope module example_1 $end
$var wire 1 " A $end
$var wire 1 # B $end
$var wire 1 $ C $end
$var wire 1 % D $end
$var wire 1 & E $end
$var wire 1 ' F $end
$var wire 1 ! Y $end
$var wire 1 ( t1 $end
$var wire 1 ) t2 $end
$var wire 1 * t3 $end
$upscope $end
$upscope $end
$enddefinitions $end
$comment Show the parameter values. $end
$dumpall
$end
#0
$dumpvars
x*
x)
x(
0'
0&
0%
0$
0#
0"
x!
$end
#1
1*
1(
#2
0)
#3
1!
#5
1%
1"
#10
1$
0"
#15
0$
1"
#20
1'
#21
0*
